<?xml version="1.0"?>

<monster id="1">
    <name>gatekeeper</name>
    <HP>35</HP>
    <ATK>5</ATK>
    <DEF>2</DEF>
    <DODGE>0</DODGE>
    <FLIGHT>0</FLIGHT>
    <SKILL_LOW>3</SKILL_LOW>
    <SKILL_HIGH>4</SKILL_HIGH>
</monster>

<monster id="2">
    <name>Predator</name>
    <HP>45</HP>
    <ATK>5</ATK>
    <DEF>2</DEF>
    <DODGE>5</DODGE>
    <FLIGHT>0</FLIGHT>
    <SKILL_LOW>5</SKILL_LOW>
    <SKILL_HIGH>6</SKILL_HIGH>
</monster>

<monster id="3">
    <name>Griffin</name>
    <HP>55</HP>
    <ATK>5</ATK>
    <DEF>2</DEF>
    <DODGE>15</DODGE>
    <FLIGHT>1</FLIGHT>
    <SKILL_LOW>7</SKILL_LOW>
    <SKILL_HIGH>8</SKILL_HIGH>
</monster>

<monster id="4">
    <name>Wraith</name>
    <HP>55</HP>
    <ATK>5</ATK>
    <DEF>2</DEF>
    <DODGE>15</DODGE>
    <FLIGHT>0</FLIGHT>
    <SKILL_LOW>9</SKILL_LOW>
    <SKILL_HIGH>10</SKILL_HIGH>
</monster>

<monster id="5">
    <name>Boss: Inferno</name>
    <HP>200</HP>
    <ATK>20</ATK>
    <DEF>20</DEF>
    <DODGE>7</DODGE>
    <FLIGHT>1</FLIGHT>
    <SKILL_LOW>11</SKILL_LOW>
    <SKILL_HIGH>12</SKILL_HIGH>
</monster>
